MANIFEST.in
setup.py
django_elfinderfs.egg-info/PKG-INFO
django_elfinderfs.egg-info/SOURCES.txt
django_elfinderfs.egg-info/dependency_links.txt
django_elfinderfs.egg-info/requires.txt
django_elfinderfs.egg-info/top_level.txt
elfinderfs/__init__.py
elfinderfs/admin.py
elfinderfs/config.py
elfinderfs/models.py
elfinderfs/serializers.py
elfinderfs/views.py
elfinderfs/migrations/0001_initial.py
elfinderfs/migrations/__init__.py
elfinderfs/static/elfinder/Changelog
elfinderfs/static/elfinder/README.md
elfinderfs/static/elfinder/elfinder.html
elfinderfs/static/elfinder/css/elfinder.min.css
elfinderfs/static/elfinder/css/theme.css
elfinderfs/static/elfinder/css/smoothness/jquery-ui.css
elfinderfs/static/elfinder/css/smoothness/jquery-ui.min.css
elfinderfs/static/elfinder/css/smoothness/theme.css
elfinderfs/static/elfinder/css/smoothness/images/ui-bg_flat_0_aaaaaa_40x100.png
elfinderfs/static/elfinder/css/smoothness/images/ui-bg_flat_75_ffffff_40x100.png
elfinderfs/static/elfinder/css/smoothness/images/ui-bg_glass_55_fbf9ee_1x400.png
elfinderfs/static/elfinder/css/smoothness/images/ui-bg_glass_65_ffffff_1x400.png
elfinderfs/static/elfinder/css/smoothness/images/ui-bg_glass_75_dadada_1x400.png
elfinderfs/static/elfinder/css/smoothness/images/ui-bg_glass_75_e6e6e6_1x400.png
elfinderfs/static/elfinder/css/smoothness/images/ui-bg_glass_95_fef1ec_1x400.png
elfinderfs/static/elfinder/css/smoothness/images/ui-bg_highlight-soft_75_cccccc_1x100.png
elfinderfs/static/elfinder/css/smoothness/images/ui-icons_222222_256x240.png
elfinderfs/static/elfinder/css/smoothness/images/ui-icons_2e83ff_256x240.png
elfinderfs/static/elfinder/css/smoothness/images/ui-icons_454545_256x240.png
elfinderfs/static/elfinder/css/smoothness/images/ui-icons_888888_256x240.png
elfinderfs/static/elfinder/css/smoothness/images/ui-icons_cd0a0a_256x240.png
elfinderfs/static/elfinder/img/arrows-active.png
elfinderfs/static/elfinder/img/arrows-normal.png
elfinderfs/static/elfinder/img/crop.gif
elfinderfs/static/elfinder/img/dialogs.png
elfinderfs/static/elfinder/img/icons-big.png
elfinderfs/static/elfinder/img/icons-small.png
elfinderfs/static/elfinder/img/logo.png
elfinderfs/static/elfinder/img/progress.gif
