Metadata-Version: 1.1
Name: django-elfinderfs
Version: 0.0.10
Summary: django-elfinderfs is a 3rd party connector for elFinder 2.x and Django. It's a simple local file system driver which does not uses any databases.
Home-page: https://pypi.python.org/pypi/django-elfinderfs
Author: Okami
Author-email: okami@fuzetsu.info
License: GPLv3
Keywords: django elfinder file manager
Platform: UNKNOWN
Classifier: Development Status :: 3 - Alpha
Classifier: Programming Language :: Python :: 3
Classifier: License :: OSI Approved :: GNU General Public License v3 or later (GPLv3+)
Classifier: Framework :: Django
